[
    {
        "Text": "#G26# As an archivist, I want to restrict a group of files from view.",
        "Persona": [
            "Archivist"
        ],
        "Entity": [
            "View",
            "File"
        ],
        "Action": [
            "Restrict A Group Of Files From View"
        ]
    },
    {
        "Text": "#G26# As an archivist, I want to set a date on which restrictions will be removed from a file, so that that I don't have to update this by hand.",
        "Persona": [
            "Archivist"
        ],
        "Entity": [
            "Date",
            "File",
            "Restriction"
        ],
        "Action": [
            "Set A Date On Which Restrictions Removed From A File"
        ]
    },
    {
        "Text": "#G26# As an archivist, I want to select existing rights statuses and statements, so that I can easily create uniform rights statements.",
        "Persona": [
            "Archivist"
        ],
        "Entity": [
            "Statement",
            "Rights Statuses"
        ],
        "Action": [
            "Select Statement",
            "Select Existing Rights Statuses"
        ]
    },
    {
        "Text": "#G26# As an archivist, I want to redact information in digital files for a period of time, so that I can provide access to non-sensitive portions of a record.",
        "Persona": [
            "Archivist"
        ],
        "Entity": [
            "Time",
            "Digital File",
            "Information"
        ],
        "Action": [
            "Redact Information In Digital Files For A Period Of Time"
        ]
    },
    {
        "Text": "#G26# As an archivist, I want to have an online form for licensing archival material, so that the process is more transparent and some of the back and forth can be eliminated.",
        "Persona": [
            "Archivist"
        ],
        "Entity": [
            "Online Form",
            "Archival Material"
        ],
        "Action": [
            "Have An Online Form Licensing Archival Material"
        ]
    },
    {
        "Text": "#G26# As an archivist, I want to automatically generate technical metadata, so that I know the file size.",
        "Persona": [
            "Archivist"
        ],
        "Entity": [
            "Technical Metadata"
        ],
        "Action": [
            "Generate Technical Metadata"
        ]
    },
    {
        "Text": "#G26# As an archivist, I want to link electronic versions of researchers' publications to citations, so that I can share them with other researchers.",
        "Persona": [
            "Archivist"
        ],
        "Entity": [
            "Publication",
            "Researcher",
            "Citation"
        ],
        "Action": [
            "Link Electronic Versions Of Researchers' Publications To Citations"
        ]
    },
    {
        "Text": "#G26# As an archivist, I want to automatically create access derivatives of digital objects, so that I don't have to do this manually.",
        "Persona": [
            "Archivist"
        ],
        "Entity": [
            "Access Derivatives",
            "Digital Object"
        ],
        "Action": [
            "Create Access Derivatives Of Digital Objects"
        ]
    },
    {
        "Text": "#G26# As an archivist, I want to automatically assign unique identifiers to material I scan, so that I avoid potential errors.",
        "Persona": [
            "Archivist"
        ],
        "Entity": [
            "Unique Identifier",
            "Material"
        ],
        "Action": [
            "Assign Unique Identifiers To Material",
            "Scan"
        ]
    },
    {
        "Text": "#G26# As a donor representative, I want to supply incremental accruals to new and existing collections, so that material can be transferred on an ongoing basis.",
        "Persona": [
            "Donor Representative"
        ],
        "Entity": [
            "New Collection",
            "Incremental Accrual"
        ],
        "Action": [
            "Exist",
            "Supply Incremental Accruals To",
            "Supply Incremental Accruals To New Collections"
        ]
    },
    {
        "Text": "#G26# As an archivist, I want to manage loan documentation, including preservation photos, forms and correspondence, so that I can find it easily later.",
        "Persona": [
            "Archivist"
        ],
        "Entity": [
            "Form",
            "Preservation Photos",
            "Documentation",
            "Correspondence",
            "Loan"
        ],
        "Action": [
            "Manage Documentation Including Form",
            "Manage Loan Documentation Including Preservation Photos",
            "Manage Documentation Including Correspondence"
        ]
    },
    {
        "Text": "#G26# As a researcher, I want to generate structured citation data, so that so I can cite a file in a publication.",
        "Persona": [
            "Researcher"
        ],
        "Entity": [
            "Citation Data"
        ],
        "Action": [
            "Generate Structured Citation Data"
        ]
    },
    {
        "Text": "#G26# As a researcher, I want to share a link to a file on social media, so that so I can show other people an interesting thing I found.",
        "Persona": [
            "Researcher"
        ],
        "Entity": [
            "Social Medium",
            "File",
            "Link"
        ],
        "Action": [
            "Share A Link To A File On Social Media"
        ]
    },
    {
        "Text": "#G26# As a researcher, I want to locate photographs and documents that I can share on social media.",
        "Persona": [
            "Researcher"
        ],
        "Entity": [
            "Photograph",
            "Social Medium",
            "Document"
        ],
        "Action": [
            "That Share On Social Media",
            "Locate Photographs",
            "Locate Document"
        ]
    },
    {
        "Text": "#G26# As a researcher, I want to stream audio and video files in my web browser.",
        "Persona": [
            "Researcher"
        ],
        "Entity": [
            "Web Browser",
            "Video",
            "Audio File"
        ],
        "Action": [
            "Stream Audio Files In Web Browser",
            "Stream Video"
        ]
    },
    {
        "Text": "#G26# As an archivist, I want to see what a particular user has downloaded, so that I can track use of assets.",
        "Persona": [
            "Archivist"
        ],
        "Entity": [
            "Particular User"
        ],
        "Action": [
            "See"
        ]
    },
    {
        "Text": "#G26# As an archivist, I want to make as much archival material as possible available for use, so that I can fulfill the RAC's mission.",
        "Persona": [
            "Archivist"
        ],
        "Entity": [
            "Archival Material"
        ],
        "Action": [
            "Possible Make As Much Archival Material"
        ]
    },
    {
        "Text": "#G26# As a researcher, I want to see common material across collections, so that so I can prepare a comprehensive analysis.",
        "Persona": [
            "Researcher"
        ],
        "Entity": [
            "Common Material",
            "Collection"
        ],
        "Action": [
            "See Common Material Across Collections"
        ]
    },
    {
        "Text": "#G26# As an archivist, I want to search all files by keyword.",
        "Persona": [
            "Archivist"
        ],
        "Entity": [
            "Keyword",
            "File"
        ],
        "Action": [
            "Search All Files By Keyword"
        ]
    },
    {
        "Text": "#G26# As an archivist, I want to upload inventories, so that our donor representatives have an easier time requesting their material.",
        "Persona": [
            "Archivist"
        ],
        "Entity": [
            "Inventory"
        ],
        "Action": [
            "Upload Inventories"
        ]
    },
    {
        "Text": "#G26# As an archivist, I want to access the digital files on the X-drive, so that I can use them.",
        "Persona": [
            "Archivist"
        ],
        "Entity": [
            "Digital File",
            "Drive"
        ],
        "Action": [
            "Access The Digital Files On The Drive"
        ]
    },
    {
        "Text": "#G26# As an archivist, I want to have electronic versions of the collection files available for staff use, so that I increase accessibility and I do not lose the original files.",
        "Persona": [
            "Archivist"
        ],
        "Entity": [
            "Staff Use",
            "Collection Files"
        ],
        "Action": [
            "Have Electronic Versions Of The Available Collection Files For Staff Use"
        ]
    },
    {
        "Text": "#G26# As a researcher, I want to have accurate cross-collection citation information, so that I can find materials again.",
        "Persona": [
            "Researcher"
        ],
        "Entity": [
            "Citation Information"
        ],
        "Action": [
            "Have Collection, Accurate Citation Information"
        ]
    },
    {
        "Text": "#G26# As a researcher, I want to search OCRed text in all available digitized textual documents, so that I can more efficiently locate digitized documents relevant to my research.",
        "Persona": [
            "Researcher"
        ],
        "Entity": [
            "Textual , Digitize , Available Document",
            "Ocred Text"
        ],
        "Action": [
            "Search Ocred Text In All Textual, Digitized, Available Documents"
        ]
    },
    {
        "Text": "#G26# As a researcher, I want to know the date on which something was digitized, so that I know if it's been digitized since I last looked.",
        "Persona": [
            "Researcher"
        ],
        "Entity": [
            "Date"
        ],
        "Action": [
            "Know The Date On Which Something Digitized"
        ]
    },
    {
        "Text": "#G26# As an archivist, I want to search index cards and other non-public finding aids, so that I can provide better research assistance.",
        "Persona": [
            "Archivist"
        ],
        "Entity": [
            "Index Cards",
            "Finding Aid"
        ],
        "Action": [
            "Search Public, Other Finding Aid",
            "Search Index Cards"
        ]
    },
    {
        "Text": "#G26# As an archivist, I want to access metadata and visual representations of index cards, so that I can use that information to assist researchers.",
        "Persona": [
            "Archivist"
        ],
        "Entity": [
            "Index Cards",
            "Visual Representation"
        ],
        "Action": [
            "Access Metadata Of Index Cards",
            "Access Visual Representation"
        ]
    },
    {
        "Text": "#G26# As an administrator, I want to assign rights to user groups or roles, so that I can control what users can and can't do.",
        "Persona": [
            "Administrator"
        ],
        "Entity": [
            "User Groups",
            "Right",
            "Role"
        ],
        "Action": [
            "Assign Rights To Role",
            "Assign Rights To User Groups"
        ]
    },
    {
        "Text": "#G26# As an administrator, I want to have researchers reset their own passwords, so that I don't have to send passwords in cleartext.",
        "Persona": [
            "Administrator"
        ],
        "Entity": [
            "Researcher",
            "Password"
        ],
        "Action": [
            "Have"
        ]
    },
    {
        "Text": "#G26# As an administrator, I want to limit who can see certain metadata fields, so that I can show or hide things from display based on user groups.",
        "Persona": [
            "Administrator"
        ],
        "Entity": [
            "Metadata Fields"
        ],
        "Action": [
            "Limit"
        ]
    }
]